CHANGELOG.rst
LICENSE.txt
README.rst
sanic_plugin_toolkit/__init__.py
sanic_plugin_toolkit/config.py
sanic_plugin_toolkit/context.py
sanic_plugin_toolkit/plugin.py
sanic_plugin_toolkit/plugins/__init__.py
sanic_plugin_toolkit/plugins/contextualize.py
sanic_plugin_toolkit/realm.py
sanic_plugin_toolkit-1.2.0.dist-info/entry_points.txt
sanic_plugin_toolkit-1.2.0.dist-info/LICENSE.txt
sanic_plugin_toolkit-1.2.0.dist-info/WHEEL
sanic_plugin_toolkit-1.2.0.dist-info/METADATA
sanic_plugin_toolkit-1.2.0.dist-info/RECORD
