Metadata-Version: 2.1
Name: sanic-plugin-toolkit
Version: 1.2.0
Summary: The all-in-one toolkit for creating powerful Sanic Plugins
Home-page: https://github.com/ashleysommer/sanicplugintoolkit
License: MIT
Keywords: sanic,plugin,toolkit
Author: Ashley Sommer
Author-email: ashleysommer@gmail.com
Requires-Python: >=3.7,<4.0
Classifier: Environment :: Web Environment
Classifier: Intended Audience :: Developers
Classifier: License :: OSI Approved :: MIT License
Classifier: Operating System :: OS Independent
Classifier: Programming Language :: Python
Classifier: Programming Language :: Python :: 3
Classifier: Programming Language :: Python :: 3.7
Classifier: Programming Language :: Python :: 3.8
Classifier: Programming Language :: Python :: 3.9
Classifier: Programming Language :: Python :: Implementation :: CPython
Classifier: Programming Language :: Python :: Implementation :: PyPy
Classifier: Topic :: Internet :: WWW/HTTP :: Dynamic Content
Classifier: Topic :: Software Development :: Libraries :: Python Modules
Requires-Dist: sanic
Requires-Dist: setuptools (>=40.8)
Project-URL: Repository, https://github.com/ashleysommer/sanicplugintoolkit
